poetry_link/__init__.py
poetry_link-0.1.6.dist-info/entry_points.txt
poetry_link-0.1.6.dist-info/WHEEL
poetry_link-0.1.6.dist-info/METADATA
poetry_link-0.1.6.dist-info/RECORD
