Metadata-Version: 2.1
Name: poetry-link
Version: 0.1.6
Summary: Editable installs for packages developed with Poetry using Flit.
Author: Niklas Rosenstein
Author-email: rosensteinniklas@gmail.com
Requires-Python: >=3.10,<4.0
Classifier: Programming Language :: Python :: 3
Classifier: Programming Language :: Python :: 3.10
Requires-Dist: poetry (>=1.2.0a2,<2.0.0)
Requires-Dist: slam-cli (>=1.0.0,<2.0.0)
